octotools/__init__.py
octotools/solver.py
octotools/engine/__init__.py
octotools/engine/anthropic.py
octotools/engine/base.py
octotools/engine/deepseek.py
octotools/engine/engine_utils.py
octotools/engine/factory.py
octotools/engine/openai.py
octotools/engine/together.py
octotools/models/__init__.py
octotools/models/executor.py
octotools/models/formatters.py
octotools/models/initializer.py
octotools/models/memory.py
octotools/models/planner.py
octotools/models/utils.py
octotools/tools/__init__.py
octotools/tools/base.py
octotools/tools/advanced_object_detector/__init__.py
octotools/tools/advanced_object_detector/tool.py
octotools/tools/arxiv_paper_searcher/__init__.py
octotools/tools/arxiv_paper_searcher/tool.py
octotools/tools/generalist_solution_generator/__init__.py
octotools/tools/generalist_solution_generator/tool.py
octotools/tools/google_search/__init__.py
octotools/tools/google_search/tool.py
octotools/tools/image_captioner/__init__.py
octotools/tools/image_captioner/tool.py
octotools/tools/nature_news_fetcher/__init__.py
octotools/tools/nature_news_fetcher/tool.py
octotools/tools/object_detector/__init__.py
octotools/tools/object_detector/tool.py
octotools/tools/pubmed_search/__init__.py
octotools/tools/pubmed_search/tool.py
octotools/tools/python_code_generator/__init__.py
octotools/tools/python_code_generator/tool.py
octotools/tools/relevant_patch_zoomer/__init__.py
octotools/tools/relevant_patch_zoomer/tool.py
octotools/tools/text_detector/__init__.py
octotools/tools/text_detector/tool.py
octotools/tools/url_text_extractor/__init__.py
octotools/tools/url_text_extractor/tool.py
octotools/tools/wikipedia_knowledge_searcher/__init__.py
octotools/tools/wikipedia_knowledge_searcher/tool.py
octotools_test_001-0.0.6.dist-info/licenses/LICENSE
octotools_test_001-0.0.6.dist-info/licenses/LICENSE-TASKS
octotools_test_001-0.0.6.dist-info/METADATA
octotools_test_001-0.0.6.dist-info/WHEEL
octotools_test_001-0.0.6.dist-info/top_level.txt
octotools_test_001-0.0.6.dist-info/RECORD
