Metadata-Version: 2.4
Name: octotools_test_001
Version: 0.0.6
Summary: An effective and easy-to-use agentic framework with extendable tools for complex reasoning.
Author-email: Pan Lu <lupantech@gmail.com>
License-Expression: MIT
Project-URL: Homepage, https://octotools.github.io
Project-URL: Paper, https://arxiv.org/pdf/2502.11271
Project-URL: Github, https://github.com/octotools/octotools
Project-URL: Issues, https://github.com/octotools/octotools/issues
Classifier: Programming Language :: Python :: 3
Classifier: Operating System :: OS Independent
Requires-Python: >=3.10
License-File: LICENSE
License-File: LICENSE-TASKS
Requires-Dist: anthropic==0.40.0
Requires-Dist: diskcache==5.6.3
Requires-Dist: easyocr==1.7.2
Requires-Dist: metapub==0.5.12
Requires-Dist: openai==1.75.0
Requires-Dist: together==1.5.4
Requires-Dist: pillow==11.1.0
Requires-Dist: platformdirs==4.3.6
Requires-Dist: pymed==0.8.9
Requires-Dist: python-dotenv==1.0.1
Requires-Dist: sympy==1.13.1
Requires-Dist: tenacity==9.0.0
Requires-Dist: transformers==4.49.0
Requires-Dist: wikipedia==1.4.0
Dynamic: license-file
